<?xml version='1.0' encoding='UTF-8'?><!DOCTYPE collection SYSTEM 'BioC.dtd'><collection><source>PubTator</source><date></date><key>BioC.key</key><document><id>10090915</id><passage><infon key="journal">Am. J. Hum. Genet.; 1999 Apr; 64(4) 1241-3</infon><infon key="year">1999</infon><infon key="article-id_pmc">PMC1377854</infon><infon key="type">title</infon><infon key="authors">Oddoux C, Clayton CM, Nelson HR, Ostrer H</infon><offset>0</offset><text>Prevalence of Bloom syndrome heterozygotes among Ashkenazi Jews.</text></passage><passage><infon key="type">abstract</infon><offset>65</offset></passage></document></collection>